{
  "matchcode" : "CCB3",
  "availableVariants" : [ {
    "matchcode" : "CCB",
    "set" : false,
    "travelSize" : false
  } ],
  "basePrice" : {
    "amount" : 1000,
    "brutto" : 993.3,
    "unit" : "g",
    "unitId" : 812
  },
  "contentsAmount" : "150",
  "currency" : "eur",
  "customerProduct" : true,
  "deliveryAddressIso" : "DE",
  "deliveryStatus" : null,
  "deliveryStatusId" : null,
  "deliveryStatusId2" : null,
  "discountDate" : null,
  "discountPercentage" : null,
  "image" : "https://i.ringana.com/2024/03/4-RINGANA-caps-cerebro-set-of-3.png?q=100",
  "isMerchandise" : false,
  "lang" : "de",
  "link" : "/produkt/caps-cerebro-set/",
  "maxPerCart" : null,
  "nemBackgroundColor" : "",
  "notSearchable" : false,
  "partnerApplicationProduct" : false,
  "partnerProduct" : true,
  "prices" : {
    "customer" : {
      "brutto" : 149,
      "bruttoWithoutDiscount" : null,
      "discountPercentage" : null,
      "discountUntil" : null,
      "initialPurchase" : {
        "brutto" : null,
        "bruttoWithoutDiscount" : null,
        "discountPercentage" : null,
        "discountUntil" : null,
        "provisionPoints" : null
      },
      "provisionPoints" : 74.4
    },
    "partner" : {
      "brutto" : 149,
      "bruttoWithoutDiscount" : null,
      "discountPercentage" : null,
      "discountUntil" : null,
      "initialPurchase" : {
        "brutto" : null,
        "bruttoWithoutDiscount" : null,
        "discountPercentage" : null,
        "discountUntil" : null,
        "provisionPoints" : null
      },
      "provisionPoints" : 74.4
    }
  },
  "purchasePossible" : true,
  "setContents" : {
    "0" : {
      "amount" : 3,
      "gratis" : false,
      "matchcode" : "CCB"
    }
  },
  "showOnFrontpage" : false,
  "singleShipmentOnly" : false,
  "skinTypes" : null,
  "soldOut" : false,
  "title" : "CAPS cerebro, Set of 3",
  "unit" : "Set",
  "unitContents" : "g",
  "unitContentsId" : 812,
  "unitId" : 43586,
  "usp" : "Gedächtnisstütze"
}