{
  "matchcode" : "CCV",
  "additionalUnitPrice" : {
    "entity" : 90,
    "type" : 1
  },
  "awards" : [ ],
  "blogPostIds" : [ 196283, 87603, 116936 ],
  "categories" : [ {
    "id" : 3,
    "infoColorNeeded" : false,
    "name" : "category.category3.name",
    "primary" : true,
    "slug" : "caps",
    "visible" : true
  }, {
    "id" : 18,
    "infoColorNeeded" : false,
    "name" : "category.category18.name",
    "primary" : false,
    "slug" : "supplements",
    "visible" : true
  }, {
    "id" : 74,
    "infoColorNeeded" : false,
    "name" : "category.category74.name",
    "primary" : false,
    "slug" : "better-aging",
    "visible" : true
  } ],
  "contentBlock" : null,
  "contentsAmount" : "52",
  "countryIso" : "DE",
  "currency" : "eur",
  "deliveryStatus" : null,
  "deliveryStatusId" : null,
  "deliveryStatusId2" : null,
  "descriptionImageId" : null,
  "discountDate" : null,
  "discountPercentage" : null,
  "disruptor" : null,
  "faqs" : [ ],
  "firstHeadline" : "",
  "id" : 82,
  "idealSupplements" : [ {
    "additionalUnitPrice" : {
      "entity" : 78,
      "type" : 2
    },
    "contentsAmount" : "1040",
    "currency" : "eur",
    "description" : "FRESH PACKS",
    "imageId" : 1141,
    "matchcode" : "WP1",
    "priceInformation" : {
      "base" : {
        "amount" : null,
        "brutto" : null,
        "unit" : null,
        "unitId" : null
      },
      "customer" : {
        "brutto" : 177.5,
        "bruttoWithoutDiscount" : null,
        "discountPercentage" : null,
        "discountUntil" : null,
        "initialPurchase" : {
          "brutto" : null,
          "bruttoWithoutDiscount" : null,
          "discountPercentage" : null,
          "discountUntil" : null,
          "provisionPoints" : null
        },
        "provisionPoints" : 86.4
      },
      "partner" : {
        "brutto" : 177.5,
        "bruttoWithoutDiscount" : null,
        "discountPercentage" : null,
        "discountUntil" : null,
        "initialPurchase" : {
          "brutto" : null,
          "bruttoWithoutDiscount" : null,
          "discountPercentage" : null,
          "discountUntil" : null,
          "provisionPoints" : null
        },
        "provisionPoints" : 86.4
      }
    },
    "purchasePossible" : true,
    "slug" : "packs-abc",
    "title" : "FRESH packs ABC",
    "unitContents" : "g"
  }, {
    "additionalUnitPrice" : null,
    "contentsAmount" : "360",
    "currency" : "eur",
    "description" : "RINGANAisi",
    "imageId" : 263,
    "matchcode" : "RI12",
    "priceInformation" : {
      "base" : {
        "amount" : 1000,
        "brutto" : 154.7,
        "unit" : "ml",
        "unitId" : 827
      },
      "customer" : {
        "brutto" : 55.7,
        "bruttoWithoutDiscount" : null,
        "discountPercentage" : null,
        "discountUntil" : null,
        "initialPurchase" : {
          "brutto" : null,
          "bruttoWithoutDiscount" : null,
          "discountPercentage" : null,
          "discountUntil" : null,
          "provisionPoints" : null
        },
        "provisionPoints" : 32
      },
      "partner" : {
        "brutto" : 55.7,
        "bruttoWithoutDiscount" : null,
        "discountPercentage" : null,
        "discountUntil" : null,
        "initialPurchase" : {
          "brutto" : null,
          "bruttoWithoutDiscount" : null,
          "discountPercentage" : null,
          "discountUntil" : null,
          "provisionPoints" : null
        },
        "provisionPoints" : 32
      }
    },
    "purchasePossible" : true,
    "slug" : "ringanaisi",
    "title" : "RINGANAisi",
    "unitContents" : "ml"
  }, {
    "additionalUnitPrice" : {
      "entity" : 60,
      "type" : 1
    },
    "contentsAmount" : "50",
    "currency" : "eur",
    "description" : "BEYOND omega",
    "imageId" : 3413,
    "matchcode" : "OME-SG",
    "priceInformation" : {
      "base" : {
        "amount" : 1000,
        "brutto" : 1772,
        "unit" : "g",
        "unitId" : 812
      },
      "customer" : {
        "brutto" : 88.6,
        "bruttoWithoutDiscount" : null,
        "discountPercentage" : null,
        "discountUntil" : null,
        "initialPurchase" : {
          "brutto" : null,
          "bruttoWithoutDiscount" : null,
          "discountPercentage" : null,
          "discountUntil" : null,
          "provisionPoints" : null
        },
        "provisionPoints" : 49.6
      },
      "partner" : {
        "brutto" : 88.6,
        "bruttoWithoutDiscount" : null,
        "discountPercentage" : null,
        "discountUntil" : null,
        "initialPurchase" : {
          "brutto" : null,
          "bruttoWithoutDiscount" : null,
          "discountPercentage" : null,
          "discountUntil" : null,
          "provisionPoints" : null
        },
        "provisionPoints" : 49.6
      }
    },
    "purchasePossible" : true,
    "slug" : "beyond-omega",
    "title" : "BEYOND omega",
    "unitContents" : "g"
  } ],
  "imageGallery" : [ {
    "caption" : "",
    "captionLink" : null,
    "id" : 716,
    "mediaId" : 1139
  }, {
    "caption" : "",
    "captionLink" : null,
    "id" : 203,
    "mediaId" : 386
  }, {
    "caption" : "",
    "captionLink" : null,
    "id" : 204,
    "mediaId" : 387
  } ],
  "infoColor" : "#ffb3ab",
  "isFreshCosmeticsProduct" : false,
  "isMerchandise" : false,
  "maxPerCart" : 100,
  "nemBackgroundColor" : null,
  "press" : null,
  "priceInformation" : {
    "base" : {
      "amount" : 1000,
      "brutto" : 1059.6,
      "unit" : "g",
      "unitId" : 812
    },
    "customer" : {
      "brutto" : 55.1,
      "bruttoWithoutDiscount" : null,
      "discountPercentage" : null,
      "discountUntil" : null,
      "initialPurchase" : {
        "brutto" : null,
        "bruttoWithoutDiscount" : null,
        "discountPercentage" : null,
        "discountUntil" : null,
        "provisionPoints" : null
      },
      "provisionPoints" : 30.6
    },
    "partner" : {
      "brutto" : 55.1,
      "bruttoWithoutDiscount" : null,
      "discountPercentage" : null,
      "discountUntil" : null,
      "initialPurchase" : {
        "brutto" : null,
        "bruttoWithoutDiscount" : null,
        "discountPercentage" : null,
        "discountUntil" : null,
        "provisionPoints" : null
      },
      "provisionPoints" : 30.6
    }
  },
  "purchasePossible" : true,
  "searchable" : true,
  "secondHeadline" : "",
  "setContents" : [ ],
  "shortDescription" : "product.CCV.shortDescription",
  "showOnSpecialOffer" : 2,
  "singleShipmentOnly" : false,
  "skinTypes" : [ ],
  "slug" : "caps-pump",
  "socialMedia" : {
    "id" : 82,
    "imageId" : 383,
    "text" : "product.CCV.socialMedia.text",
    "title" : "product.CCV.socialMedia.title"
  },
  "soldOut" : false,
  "supplementDescription" : "CAPS pump",
  "tabs" : [ {
    "description" : "product.CCV.tabs0.description",
    "id" : 308,
    "showPrintButton" : false,
    "title" : "product.CCV.tabs0.title"
  }, {
    "description" : "product.CCV.tabs1.description",
    "id" : 309,
    "showPrintButton" : true,
    "title" : "product.CCV.tabs1.title"
  }, {
    "description" : "product.CCV.tabs2.description",
    "id" : 310,
    "showPrintButton" : false,
    "title" : "product.CCV.tabs2.title"
  }, {
    "description" : "product.CCV.tabs3.description",
    "id" : 311,
    "showPrintButton" : false,
    "title" : "product.CCV.tabs3.title"
  } ],
  "teaserDots" : [ ],
  "title" : "CAPS pump",
  "unit" : "Pck.",
  "unitContents" : "g",
  "unitContentsId" : 812,
  "unitId" : 43589,
  "usp" : "product.CCV.usp",
  "values" : [ {
    "iconMediaId" : 1061,
    "name" : "value.value6.name"
  }, {
    "iconMediaId" : 1112,
    "name" : "value.value57.name"
  }, {
    "iconMediaId" : 1095,
    "name" : "value.value40.name"
  }, {
    "iconMediaId" : 1080,
    "name" : "value.value25.name"
  }, {
    "iconMediaId" : 1121,
    "name" : "value.value66.name"
  } ],
  "variants" : [ {
    "color" : null,
    "id" : 136,
    "language" : null,
    "matchcode" : "CCV",
    "name" : null,
    "size" : 90,
    "slug" : "caps-pump",
    "type" : 2,
    "unit" : 1
  }, {
    "color" : null,
    "id" : 137,
    "language" : null,
    "matchcode" : "CCV3",
    "name" : null,
    "size" : 270,
    "slug" : "caps-pump-set",
    "type" : 2,
    "unit" : 1
  } ]
}