{
  "matchcode" : "COV3",
  "availableVariants" : [ {
    "matchcode" : "COV",
    "set" : false,
    "travelSize" : false,
    "unit" : "Stk.",
    "unitId" : 996
  } ],
  "basePrice" : {
    "amount" : 1,
    "brutto" : 1.16,
    "unit" : "Kapsel",
    "unitId" : 43580
  },
  "contentsAmount" : "180",
  "currency" : "eur",
  "deliveryStatus" : null,
  "deliveryStatusId" : null,
  "deliveryStatusId2" : null,
  "discountDate" : null,
  "discountPercentage" : null,
  "image" : "https://i.ringana.com/2021/10/ringana-caps-omega_Set_of_3.png?q=100",
  "isMerchandise" : false,
  "lang" : "de",
  "link" : "/produkt/beyond-omega-set/",
  "maxPerCart" : null,
  "nemBackgroundColor" : "",
  "notSearchable" : false,
  "partnerApplicationProduct" : false,
  "partnerProduct" : false,
  "prices" : {
    "customer" : {
      "brutto" : 208.26,
      "bruttoWithoutDiscount" : 231.4,
      "discountPercentage" : 10,
      "discountUntil" : "2022-02-18T09:00:00Z",
      "initialPurchase" : {
        "brutto" : 208.26,
        "bruttoWithoutDiscount" : 231.4,
        "discountPercentage" : 10,
        "discountUntil" : "2022-02-18T09:00:00Z",
        "provisionPoints" : 103.68
      },
      "provisionPoints" : 103.68
    },
    "partner" : {
      "brutto" : 208.26,
      "bruttoWithoutDiscount" : 231.4,
      "discountPercentage" : 10,
      "discountUntil" : "2022-02-18T09:00:00Z",
      "initialPurchase" : {
        "brutto" : 208.26,
        "bruttoWithoutDiscount" : 231.4,
        "discountPercentage" : 10,
        "discountUntil" : "2022-02-18T09:00:00Z",
        "provisionPoints" : 103.68
      },
      "provisionPoints" : 103.68
    }
  },
  "purchasePossible" : true,
  "setContents" : {
    "0" : {
      "amount" : 3,
      "gratis" : false,
      "matchcode" : "COV"
    }
  },
  "showOnFrontpage" : false,
  "singleShipmentOnly" : false,
  "skinTypes" : null,
  "soldOut" : false,
  "title" : "BEYOND omega, Set of 3",
  "unit" : "Set",
  "unitContents" : "Kap.",
  "unitContentsId" : 804,
  "unitId" : 43586,
  "usp" : "Life Essentials"
}