{
  "matchcode" : "PCN",
  "availableVariants" : [ ],
  "basePrice" : {
    "amount" : 1000,
    "brutto" : 2544,
    "unit" : "ml",
    "unitId" : 827
  },
  "contentsAmount" : "5",
  "currency" : "eur",
  "customerProduct" : true,
  "deliveryAddressIso" : "DE",
  "deliveryStatus" : null,
  "deliveryStatusId" : null,
  "deliveryStatusId2" : null,
  "discountDate" : null,
  "discountPercentage" : null,
  "image" : "https://i.ringana.com/2024/03/RINGANA-fresh-overnight-face-treatment-sample.png?q=100",
  "isMerchandise" : false,
  "lang" : "de",
  "link" : "/produkt/fresh-overnight-face-treatment-sample/",
  "maxPerCart" : 99999,
  "nemBackgroundColor" : "",
  "notSearchable" : false,
  "partnerApplicationProduct" : false,
  "partnerProduct" : true,
  "prices" : {
    "customer" : {
      "brutto" : 12.72,
      "bruttoWithoutDiscount" : 15.9,
      "discountPercentage" : 20,
      "discountUntil" : "2024-06-03T21:59:59Z",
      "initialPurchase" : {
        "brutto" : null,
        "bruttoWithoutDiscount" : null,
        "discountPercentage" : null,
        "discountUntil" : null,
        "provisionPoints" : null
      },
      "provisionPoints" : 5.62
    },
    "partner" : {
      "brutto" : 12.72,
      "bruttoWithoutDiscount" : 15.9,
      "discountPercentage" : 20,
      "discountUntil" : "2024-06-03T21:59:59Z",
      "initialPurchase" : {
        "brutto" : null,
        "bruttoWithoutDiscount" : null,
        "discountPercentage" : null,
        "discountUntil" : null,
        "provisionPoints" : null
      },
      "provisionPoints" : 5.62
    }
  },
  "purchasePossible" : true,
  "setContents" : { },
  "showOnFrontpage" : false,
  "singleShipmentOnly" : false,
  "skinTypes" : null,
  "soldOut" : false,
  "title" : "FRESH overnight face treatment sample",
  "unit" : "Reisegröße",
  "unitContents" : "ml",
  "unitContentsId" : 827,
  "unitId" : 43592,
  "usp" : "Intensive Better-Aging-Creme für das Gesicht"
}